{
    "total_target": 450,
    "videos_per_class": {
        "ankle": 50,
        "calf": 50,
        "hamstring": 48,
        "heel_slide": 50,
        "hip": 45,
        "knee": 43,
        "leg_raise": 50,
        "quadriceps": 50,
        "toes": 50
    },
    "rejected_videos": 0,
    "videos_pending_manual_review": 0,
    "duplicate_count": 10,
    "missing_videos_per_class": {
        "ankle": 0,
        "calf": 0,
        "hamstring": 2,
        "heel_slide": 0,
        "hip": 5,
        "knee": 7,
        "leg_raise": 0,
        "quadriceps": 0,
        "toes": 0
    }
}